{
	"backtrace" : 0,
	"backtraceGraph" : 
	{
		"commands" : [],
		"files" : 
		[
			"DisposeAbstract/DisposeIMG/CMakeLists.txt"
		],
		"nodes" : 
		[
			{
				"file" : 0
			}
		]
	},
	"dependencies" : 
	[
		{
			"id" : "mytxt_img_autogen_timestamp_deps::@b35f1dbe17117d7379f7"
		}
	],
	"id" : "mytxt_img_autogen::@b35f1dbe17117d7379f7",
	"isGeneratorProvided" : true,
	"name" : "mytxt_img_autogen",
	"paths" : 
	{
		"build" : "DisposeAbstract/DisposeIMG",
		"source" : "DisposeAbstract/DisposeIMG"
	},
	"sourceGroups" : 
	[
		{
			"name" : "",
			"sourceIndexes" : 
			[
				0
			]
		},
		{
			"name" : "CMake Rules",
			"sourceIndexes" : 
			[
				1,
				2
			]
		}
	],
	"sources" : 
	[
		{
			"backtrace" : 0,
			"isGenerated" : true,
			"path" : ".build/Release/DisposeAbstract/DisposeIMG/CMakeFiles/mytxt_img_autogen",
			"sourceGroupIndex" : 0
		},
		{
			"backtrace" : 0,
			"isGenerated" : true,
			"path" : ".build/Release/DisposeAbstract/DisposeIMG/CMakeFiles/mytxt_img_autogen.rule",
			"sourceGroupIndex" : 1
		},
		{
			"backtrace" : 0,
			"isGenerated" : true,
			"path" : ".build/Release/DisposeAbstract/DisposeIMG/mytxt_img_autogen/timestamp.rule",
			"sourceGroupIndex" : 1
		}
	],
	"type" : "UTILITY"
}
